allzpark/__init__.py
allzpark/__main__.py
allzpark/__version__.py
allzpark/_rezapi.py
allzpark/allzparkconfig.py
allzpark/cli.py
allzpark/control.py
allzpark/delegates.py
allzpark/dock.py
allzpark/model.py
allzpark/resources.py
allzpark/util.py
allzpark/version.py
allzpark/view.py
allzpark/resources/Action_GoDown_3_32.png
allzpark/resources/Action_GoHome_32.png
allzpark/resources/Action_GoUp_3_Large_32.png
allzpark/resources/Action_Stop_1_32.png
allzpark/resources/Alert_Info_32.png
allzpark/resources/Alert_Warning_32.png
allzpark/resources/App_Generic_4_32.png
allzpark/resources/App_Heidi_32.png
allzpark/resources/App_Pulse_32.png
allzpark/resources/Default_Profile.png
allzpark/resources/File_Archive_32.png
allzpark/resources/File_Query_32.png
allzpark/resources/Logo_128.png
allzpark/resources/Logo_64.png
allzpark/resources/Prefs_Screen_32.png
allzpark/resources/branch_closed-on-dim.png
allzpark/resources/branch_closed-on.png
allzpark/resources/branch_closed.png
allzpark/resources/branch_open-on-dim.png
allzpark/resources/branch_open-on.png
allzpark/resources/branch_open.png
allzpark/resources/chat-square-dots-fill.svg
allzpark/resources/check-circle-fill.svg
allzpark/resources/checkbox_checked.png
allzpark/resources/checkbox_checked_bright.png
allzpark/resources/checkbox_checked_dim.png
allzpark/resources/checkbox_unchecked.png
allzpark/resources/checkbox_unchecked_bright.png
allzpark/resources/checkbox_unchecked_dim.png
allzpark/resources/collapse.svg
allzpark/resources/down_arrow.png
allzpark/resources/down_arrow_dim.png
allzpark/resources/down_arrow_disabled.png
allzpark/resources/exclamation-circle-fill.svg
allzpark/resources/expand.svg
allzpark/resources/filter_off.svg
allzpark/resources/filter_on.svg
allzpark/resources/gear-fill.svg
allzpark/resources/profile_current.svg
allzpark/resources/profile_current_star.svg
allzpark/resources/profile_normal.svg
allzpark/resources/profile_normal_star.svg
allzpark/resources/refresh.svg
allzpark/resources/star_bright.svg
allzpark-1.3.129.dist-info/METADATA
allzpark-1.3.129.dist-info/WHEEL
allzpark-1.3.129.dist-info/entry_points.txt
allzpark-1.3.129.dist-info/top_level.txt
allzpark-1.3.129.dist-info/RECORD
