Metadata-Version: 2.1
Name: allzpark
Version: 1.3.129
Summary: A cross-platform launcher for film and games projects, built on Rez
Home-page: https://github.com/mottosso/allzpark
Author: Marcus Ottosson
Author-email: konstruktion@gmail.com
License: LGPL
Keywords: launcher package resolve version software management
Platform: UNKNOWN
Classifier: Development Status :: 4 - Beta
Classifier: License :: OSI Approved :: GNU Lesser General Public License v3 (LGPLv3)
Classifier: Intended Audience :: Developers
Classifier: Operating System :: OS Independent
Classifier: Programming Language :: Python
Classifier: Programming Language :: Python :: 2
Classifier: Programming Language :: Python :: 2.7
Classifier: Programming Language :: Python :: 3
Classifier: Programming Language :: Python :: 3.6
Classifier: Programming Language :: Python :: 3.7
Classifier: Topic :: Utilities
Classifier: Topic :: Software Development
Classifier: Topic :: Software Development :: Libraries :: Python Modules
Requires-Python: >2.7, <4
Requires-Dist: bleeding-rez (>=2.38.2)
Requires-Dist: allzparkdemo (>=1)
Requires-Dist: PySide ; python_version < "3"
Requires-Dist: PySide2 ; python_version > "3"
